micropython_adt7410/__init__.py
micropython_adt7410/adt7410.py
micropython_adt7410/i2c_helpers.py
micropython_adt7410-0.2.0.dist-info/LICENSE
micropython_adt7410-0.2.0.dist-info/METADATA
micropython_adt7410-0.2.0.dist-info/WHEEL
micropython_adt7410-0.2.0.dist-info/top_level.txt
micropython_adt7410-0.2.0.dist-info/RECORD
