Metadata-Version: 2.1
Name: micropython-adt7410
Version: 0.2.0
Summary: MicroPython Driver for the Analog Devices ADT7410 Temperature Sensor
Author-email: JDM <xxyx@mailmeto.mozmail.com>
License: MIT
Project-URL: Homepage, https://github.com/jposada202020/MicroPython_ADT7410
Keywords: sensor,adt7410,temperature,driver,micropython
Classifier: Intended Audience :: Developers
Classifier: Topic :: Software Development :: Libraries
Classifier: Topic :: Software Development :: Embedded Systems
Classifier: Topic :: System :: Hardware
Classifier: License :: OSI Approved :: MIT License
Classifier: Programming Language :: Python :: Implementation :: MicroPython
License-File: LICENSE
